odoo8_addon_partner_report_open_invoices-8.0.1.0.0-py2.7-nspkg.pth
odoo8_addon_partner_report_open_invoices-8.0.1.0.0.dist-info/DESCRIPTION.rst
odoo8_addon_partner_report_open_invoices-8.0.1.0.0.dist-info/METADATA
odoo8_addon_partner_report_open_invoices-8.0.1.0.0.dist-info/RECORD
odoo8_addon_partner_report_open_invoices-8.0.1.0.0.dist-info/WHEEL
odoo8_addon_partner_report_open_invoices-8.0.1.0.0.dist-info/metadata.json
odoo8_addon_partner_report_open_invoices-8.0.1.0.0.dist-info/namespace_packages.txt
odoo8_addon_partner_report_open_invoices-8.0.1.0.0.dist-info/top_level.txt
odoo_addons/partner_report_open_invoices/README.rst
odoo_addons/partner_report_open_invoices/__init__.py
odoo_addons/partner_report_open_invoices/__openerp__.py
odoo_addons/partner_report_open_invoices/i18n/it.po
odoo_addons/partner_report_open_invoices/models/__init__.py
odoo_addons/partner_report_open_invoices/models/res_company.py
odoo_addons/partner_report_open_invoices/report/__init__.py
odoo_addons/partner_report_open_invoices/report/report_open_invoices.py
odoo_addons/partner_report_open_invoices/static/description/icon.png
odoo_addons/partner_report_open_invoices/tests/__init__.py
odoo_addons/partner_report_open_invoices/tests/test_partner_report_open_invoices.py
odoo_addons/partner_report_open_invoices/views/report_open_invoices_view.xml
odoo_addons/partner_report_open_invoices/views/report_paperformat.xml
odoo_addons/partner_report_open_invoices/views/res_company_view.xml
